inkparse/__init__.py
inkparse/constants.py
inkparse/general.py
inkparse/main.py
inkparse/py.typed
inkparse-0.3.2.dist-info/METADATA
inkparse-0.3.2.dist-info/WHEEL
inkparse-0.3.2.dist-info/licenses/LICENCE
inkparse-0.3.2.dist-info/RECORD
