Metadata-Version: 2.4
Name: inkparse
Version: 0.3.2
Summary: Functions and classes for recursive descent parsing.
Project-URL: Homepage, https://github.com/MoonMountain2k/inkparse
Project-URL: Issues, https://github.com/MoonMountain2k/inkparse/issues
Author-email: MoonMountain2k <moonmountain2k@gmail.com>
License-File: LICENCE
Classifier: License :: OSI Approved :: MIT License
Classifier: Operating System :: OS Independent
Classifier: Programming Language :: Python :: 3
Requires-Python: >=3.11
